Metadata-Version: 2.1
Name: django-tabbed-admin2
Version: 2.0.1
Summary: 
Author: 4Sigma
Author-email: devops@4sigma.it
Requires-Python: >=3.8,<4.0
Classifier: Programming Language :: Python :: 3
Classifier: Programming Language :: Python :: 3.8
Classifier: Programming Language :: Python :: 3.9
Classifier: Programming Language :: Python :: 3.10
Classifier: Programming Language :: Python :: 3.11
Classifier: Programming Language :: Python :: 3.12
